covid_vir_assistant/__init__.py
covid_vir_assistant-0.0.2.dist-info/LICENSE
covid_vir_assistant-0.0.2.dist-info/METADATA
covid_vir_assistant-0.0.2.dist-info/WHEEL
covid_vir_assistant-0.0.2.dist-info/top_level.txt
covid_vir_assistant-0.0.2.dist-info/RECORD
