Metadata-Version: 2.1
Name: covid-vir-assistant
Version: 0.0.2
Summary: A small example about virtual assitant like Siri/ Google assistant
Home-page: https://github.com/TrinhAnBinh/covid_vir_assistant
Author: TrinhAnBinh
Author-email: binhta1995@gmail.com
License: UNKNOWN
Platform: UNKNOWN
Classifier: Programming Language :: Python :: 3
Classifier: License :: OSI Approved :: MIT License
Classifier: Operating System :: OS Independent
Requires-Python: >=3
